seinfeld/__init__.py
seinfeld_lang-0.0.2.dist-info/LICENSE
seinfeld_lang-0.0.2.dist-info/METADATA
seinfeld_lang-0.0.2.dist-info/WHEEL
seinfeld_lang-0.0.2.dist-info/top_level.txt
seinfeld_lang-0.0.2.dist-info/RECORD
