Metadata-Version: 2.1
Name: seinfeld-lang
Version: 0.0.2
Summary: A programming language about nothing.
Home-page: http://seinfeld-lang.com/
Author: Grant Jenks
Author-email: contact@grantjenks.com
License: Apache 2.0
Platform: UNKNOWN
Classifier: Development Status :: 1 - Planning
Classifier: Intended Audience :: Developers
Classifier: License :: OSI Approved :: Apache Software License
Classifier: Natural Language :: English
Classifier: Programming Language :: Python
Classifier: Programming Language :: Python :: 3
Classifier: Programming Language :: Python :: 3.6
Classifier: Programming Language :: Python :: Implementation :: CPython
